turludock/__init__.py
turludock/__main__.py
turludock/assets/__init__.py
turludock/assets/config_files/__init__.py
turludock/assets/config_files/nvidia_cuda.yaml
turludock/assets/config_files/nvidia_cudnn.yaml
turludock/assets/default_image_configurations/__init__.py
turludock/assets/default_image_configurations/humble_mesa.yaml
turludock/assets/default_image_configurations/humble_nvidia.yaml
turludock/assets/default_image_configurations/humble_nvidia_cuda.yaml
turludock/assets/default_image_configurations/humble_nvidia_cudnn.yaml
turludock/assets/default_image_configurations/iron_mesa.yaml
turludock/assets/default_image_configurations/iron_nvidia.yaml
turludock/assets/default_image_configurations/iron_nvidia_cuda.yaml
turludock/assets/default_image_configurations/iron_nvidia_cudnn.yaml
turludock/assets/default_image_configurations/jazzy_mesa.yaml
turludock/assets/default_image_configurations/jazzy_nvidia.yaml
turludock/assets/default_image_configurations/noetic_mesa.yaml
turludock/assets/default_image_configurations/noetic_nvidia.yaml
turludock/assets/default_image_configurations/noetic_nvidia_cuda.yaml
turludock/assets/default_image_configurations/noetic_nvidia_cudnn.yaml
turludock/assets/dockerfile_assets/__init__.py
turludock/assets/dockerfile_assets/entrypoint_setup.sh
turludock/assets/dockerfile_assets/terminator_config
turludock/assets/dockerfile_templates/__init__.py
turludock/assets/dockerfile_templates/cmake.txt
turludock/assets/dockerfile_templates/cmd.txt
turludock/assets/dockerfile_templates/common_env_config.txt
turludock/assets/dockerfile_templates/conan.txt
turludock/assets/dockerfile_templates/cpplint.txt
turludock/assets/dockerfile_templates/entrypoint.txt
turludock/assets/dockerfile_templates/extra_packages_label.txt
turludock/assets/dockerfile_templates/from.txt
turludock/assets/dockerfile_templates/from_2404.txt
turludock/assets/dockerfile_templates/header_info.txt
turludock/assets/dockerfile_templates/install_common_packages.txt
turludock-3.2.0.dist-info/LICENSE
turludock-3.2.0.dist-info/METADATA
turludock-3.2.0.dist-info/WHEEL
turludock-3.2.0.dist-info/entry_points.txt
turludock-3.2.0.dist-info/RECORD
