Metadata-Version: 2.1
Name: turludock
Version: 3.2.0
Summary: Builds ROS docker images that support GUI with either X11 or Wayland.
Home-page: https://github.com/turlucode/ros-docker-gui
License: BSD 3-Clause License
Keywords: ros,docker
Author: Athanasios
Author-email: dev@tasoglou.net
Requires-Python: >=3.9,<4.0
Classifier: Development Status :: 5 - Production/Stable
Classifier: Environment :: Console
Classifier: Intended Audience :: Developers
Classifier: License :: Other/Proprietary License
Classifier: Natural Language :: English
Classifier: Operating System :: POSIX :: Linux
Classifier: Programming Language :: Python :: 3
Classifier: Programming Language :: Python :: 3.9
Classifier: Programming Language :: Python :: 3.10
Classifier: Programming Language :: Python :: 3.11
Classifier: Programming Language :: Python :: 3.12
Classifier: Topic :: Software Development :: Build Tools
Classifier: Typing :: Typed
Requires-Dist: black (>=24.4.2,<25.0.0)
Requires-Dist: docker (==7.0.0)
Requires-Dist: isort (>=5.13.2,<6.0.0)
Requires-Dist: loguru (>=0.7.2,<0.8.0)
Requires-Dist: pyproject-flake8 (>=7.0.0,<8.0.0)
Requires-Dist: pyyaml (==6.0.1)
Requires-Dist: requests (==2.26.0)
Requires-Dist: rich (==13.7.1)
Requires-Dist: termcolor (==2.4.0)
Requires-Dist: toml (>=0.10.2,<0.11.0)
Project-URL: Repository, https://github.com/turlucode/ros-docker-gui
